ratcatcher/__init__.py
ratcatcher/omniserver.py
ratcatcher/ratcatcher.py
ratcatcher-1.0.0.dist-info/LICENSE
ratcatcher-1.0.0.dist-info/METADATA
ratcatcher-1.0.0.dist-info/WHEEL
ratcatcher-1.0.0.dist-info/entry_points.txt
ratcatcher-1.0.0.dist-info/top_level.txt
ratcatcher-1.0.0.dist-info/RECORD
