Metadata-Version: 2.1
Name: ratcatcher
Version: 1.0.0
Summary: Monitor and collect suspicious network traffic
Home-page: https://github.com/LLCZ00/RATCatcher
Author: LLCZ00
License: Apache 2.0
Keywords: malware analysis detection
Classifier: Development Status :: 5 - Production/Stable
Classifier: Intended Audience :: Information Technology
Classifier: Intended Audience :: Developers
Classifier: License :: OSI Approved :: Apache Software License
Classifier: Natural Language :: English
Classifier: Programming Language :: Python :: 3
Classifier: Operating System :: OS Independent
Classifier: Topic :: Security
Classifier: Topic :: Utilities
Requires-Python: >=3.8
License-File: LICENSE
Requires-Dist: psutil (==5.9.3)
Requires-Dist: scapy (==2.4.5)
